odoo8_addon_stock_picking_send_by_mail-8.0.1.0.0-py2.7-nspkg.pth
odoo8_addon_stock_picking_send_by_mail-8.0.1.0.0.dist-info/METADATA
odoo8_addon_stock_picking_send_by_mail-8.0.1.0.0.dist-info/RECORD
odoo8_addon_stock_picking_send_by_mail-8.0.1.0.0.dist-info/WHEEL
odoo8_addon_stock_picking_send_by_mail-8.0.1.0.0.dist-info/namespace_packages.txt
odoo8_addon_stock_picking_send_by_mail-8.0.1.0.0.dist-info/top_level.txt
odoo_addons/stock_picking_send_by_mail/README.rst
odoo_addons/stock_picking_send_by_mail/__init__.py
odoo_addons/stock_picking_send_by_mail/__openerp__.py
odoo_addons/stock_picking_send_by_mail/data/stock_picking_mail.xml
odoo_addons/stock_picking_send_by_mail/i18n/de.po
odoo_addons/stock_picking_send_by_mail/i18n/es.po
odoo_addons/stock_picking_send_by_mail/i18n/fr.po
odoo_addons/stock_picking_send_by_mail/i18n/it.po
odoo_addons/stock_picking_send_by_mail/i18n/pt_BR.po
odoo_addons/stock_picking_send_by_mail/i18n/stock_picking_send_by_mail.pot
odoo_addons/stock_picking_send_by_mail/models/__init__.py
odoo_addons/stock_picking_send_by_mail/models/stock_picking.py
odoo_addons/stock_picking_send_by_mail/static/description/icon.png
odoo_addons/stock_picking_send_by_mail/tests/__init__.py
odoo_addons/stock_picking_send_by_mail/tests/test_stock_picking_send_by_mail.py
odoo_addons/stock_picking_send_by_mail/views/stock_picking_view.xml
