Metadata-Version: 2.1
Name: odoo8-addon-stock-picking-send-by-mail
Version: 8.0.1.0.0
Summary: Send stock picking by email
Home-page: https://github.com/OCA/stock-logistics-workflow
Author: Sandra Figueroa Varela, Tecnativa, Odoo Community Association (OCA)
Author-email: support@odoo-community.org
License: AGPL-3
Platform: UNKNOWN
Classifier: Programming Language :: Python
Classifier: Framework :: Odoo
Classifier: License :: OSI Approved :: GNU Affero General Public License v3
Requires-Python: ~=2.7
Requires-Dist: odoo (<9.0a,>=8.0a)
